README.rst
setup.py
pypi_librarian/__init__.py
pypi_librarian/__main__.py
pypi_librarian/_version.py
pypi_librarian/class_package.py
pypi_librarian/class_project.py
pypi_librarian/class_repo.py
pypi_librarian/class_user.py
pypi_librarian/download.py
pypi_librarian/fetch_metadata.py
pypi_librarian/html_endpoints.py
pypi_librarian/json_endpoints.py
pypi_librarian/meta_file.py
pypi_librarian/pip_endpoints.py
pypi_librarian/pypi_versions.py
pypi_librarian/qypi_endpoints.py
pypi_librarian/rss_endpoints.py
pypi_librarian/utils.py
pypi_librarian/xml_rpc_endpoints.py
pypi_librarian/yolk_endpoints.py
pypi_librarian.egg-info/PKG-INFO
pypi_librarian.egg-info/SOURCES.txt
pypi_librarian.egg-info/dependency_links.txt
pypi_librarian.egg-info/entry_points.txt
pypi_librarian.egg-info/requires.txt
pypi_librarian.egg-info/top_level.txt
test/test_class_tree.py
test/test_doc_opts.py
test/test_download_metadata.py
test/test_endpoints.py
test/test_package_downloader.py
test/test_search.py
test/test_version_check.py