Metadata-Version: 1.1
Name: pypi-librarian
Version: 0.1.9
Summary: Pypi metadata client. Client for metadata related API endpoints for Pypi.
Home-page: https://github.com/matthewdeanmartin/pypi_librarian
Author: Matthew Martin
Author-email: matthewdeanmartin@gmail.com
License: MIT
Keywords: pypi,package metadata
Platform: UNKNOWN
Classifier: Programming Language :: Python
Classifier: Programming Language :: Python :: 3.5
Classifier: Programming Language :: Python :: 3.6
Classifier: Programming Language :: Python :: Implementation :: CPython
